EqualClustPath/__init__.py
EqualClustPath/equalclustpath.py
tests/__init__.py
tests/test_clustering.py
EqualClustPath-0.2.0.dist-info/LICENSE.txt
EqualClustPath-0.2.0.dist-info/METADATA
EqualClustPath-0.2.0.dist-info/WHEEL
EqualClustPath-0.2.0.dist-info/top_level.txt
EqualClustPath-0.2.0.dist-info/RECORD
