Metadata-Version: 2.1
Name: EqualClustPath
Version: 0.2.0
Summary: A package for balanced K-means++ clustering and path planning
Home-page: https://github.com/Wild-Lemon/EqualClustPath
Author: Jiawen Hu
Author-email: dingqi2pi@gmail.com
License: MIT
Classifier: Programming Language :: Python :: 3
Classifier: License :: OSI Approved :: MIT License
Classifier: Operating System :: OS Independent
Requires-Python: >=3.6
License-File: LICENSE.txt
Requires-Dist: numpy
Requires-Dist: matplotlib
Requires-Dist: scikit-learn
